runHiC/__init__.py
runHiC/binning.py
runHiC/filtering.py
runHiC/mapping.py
runHiC/phase.py
runHiC/quality.py
runHiC/utilities.py
runHiC-0.9.0.data/scripts/runHiC
runHiC-0.9.0.data/scripts/runHiC-digest
runHiC-0.9.0.data/scripts/runHiC-phase
runHiC-0.9.0.dist-info/LICENSE
runHiC-0.9.0.dist-info/METADATA
runHiC-0.9.0.dist-info/WHEEL
runHiC-0.9.0.dist-info/top_level.txt
runHiC-0.9.0.dist-info/RECORD
