Metadata-Version: 2.1
Name: runHiC
Version: 0.9.0
Summary: A easy-to-use Hi-C processing software supporting distributed computation
Home-page: https://github.com/XiaoTaoWang/HiC_pipeline
Author: XiaoTao Wang
Author-email: wangxiaotao686@gmail.com
Keywords: Hi-C Arima ICE cooler pairs bioinformatics pipeline
Classifier: Programming Language :: Python :: 3 :: Only
Classifier: License :: OSI Approved :: GNU General Public License v3 or later (GPLv3+)
Classifier: Operating System :: POSIX
Classifier: Development Status :: 4 - Beta
Classifier: Intended Audience :: Science/Research
Classifier: Topic :: Scientific/Engineering :: Bio-Informatics
License-File: LICENSE
